page_object/__init__.py
page_object/accessors.py
page_object/browser.py
page_object/browser_factory.py
page_object/locator.py
page_object/locator_generator.py
page_object/page_factory.py
page_object/page_object.py
page_object/elements/__init__.py
page_object/elements/button.py
page_object/elements/checkbox.py
page_object/elements/div.py
page_object/elements/element.py
page_object/elements/heading.py
page_object/elements/image.py
page_object/elements/label.py
page_object/elements/link.py
page_object/elements/option.py
page_object/elements/paragraph.py
page_object/elements/radio_button.py
page_object/elements/select_list.py
page_object/elements/span.py
page_object/elements/substitute_web_element.py
page_object/elements/table.py
page_object/elements/table_cell.py
page_object/elements/table_row.py
page_object/elements/text_area.py
page_object/elements/text_field.py
page_object/expected_conditions/__init__.py
page_object/expected_conditions/element_exists.py
page_object/expected_conditions/element_predicate.py
page_object-0.3.4.dist-info/METADATA
page_object-0.3.4.dist-info/RECORD
page_object-0.3.4.dist-info/WHEEL
page_object-0.3.4.dist-info/top_level.txt
