Metadata-Version: 2.1
Name: page-object
Version: 0.3.4
Summary: Python implementation of the PageObject pattern
Home-page: https://github.com/OnShift/page_object
Author: Onshift Inc.
Author-email: dev@onshift.com
License: Apache 2.0
Keywords: page_object,selenium,webdriver
Platform: UNKNOWN
Requires-Dist: pyvirtualdisplay (==0.2)
Requires-Dist: selenium (==3.4.3)
